mf2py/__init__.py
mf2py/backcompat-rules/adr.json
mf2py/backcompat-rules/geo.json
mf2py/backcompat-rules/hentry.json
mf2py/backcompat-rules/hfeed.json
mf2py/backcompat-rules/hproduct.json
mf2py/backcompat-rules/hrecipe.json
mf2py/backcompat-rules/hresume.json
mf2py/backcompat-rules/hreview-aggregate.json
mf2py/backcompat-rules/hreview.json
mf2py/backcompat-rules/vcard.json
mf2py/backcompat-rules/vevent.json
mf2py/backcompat.py
mf2py/datetime_helpers.py
mf2py/dom_helpers.py
mf2py/implied_properties.py
mf2py/metaformats.py
mf2py/mf2_classes.py
mf2py/mf_helpers.py
mf2py/parse_property.py
mf2py/parser.py
mf2py/temp_fixes.py
mf2py/value_class_pattern.py
mf2py/version.py
mf2py-2.0.0.dist-info/METADATA
mf2py-2.0.0.dist-info/WHEEL
mf2py-2.0.0.dist-info/LICENSE
mf2py-2.0.0.dist-info/RECORD
