Metadata-Version: 2.1
Name: mf2py
Version: 2.0.0
Summary: Microformats parser
License: MIT
Author: Tom Morris
Author-email: tom@tommorris.org
Requires-Python: >=3.8
Classifier: Intended Audience :: Developers
Classifier: License :: OSI Approved :: MIT License
Classifier: Programming Language :: Python :: 3
Classifier: Programming Language :: Python :: 3.8
Classifier: Programming Language :: Python :: 3.9
Classifier: Programming Language :: Python :: 3.10
Classifier: Programming Language :: Python :: 3.11
Classifier: Programming Language :: Python :: 3
Classifier: Topic :: Text Processing :: Markup :: HTML
Requires-Dist: beautifulsoup4 (>=4.11.1,<5.0.0)
Requires-Dist: html5lib (>=1.1,<2.0)
Requires-Dist: requests (>=2.28.2,<3.0.0)
